zbricklib/__init__.py
zbricklib/extension.py
zbricklib/py.typed
zbricklib-0.1.1.dist-info/METADATA
zbricklib-0.1.1.dist-info/WHEEL
zbricklib-0.1.1.dist-info/RECORD
